AUTHORS
LICENSE
MANIFEST.in
VERSION
requirements.txt
setup.py
fauxquests/VERSION
fauxquests/__init__.py
fauxquests/adapter.py
fauxquests/compat.py
fauxquests/exceptions.py
fauxquests/messages.py
fauxquests/response.py
fauxquests/session.py
fauxquests/utils.py
fauxquests.egg-info/PKG-INFO
fauxquests.egg-info/SOURCES.txt
fauxquests.egg-info/dependency_links.txt
fauxquests.egg-info/requires.txt
fauxquests.egg-info/top_level.txt